LICENSE
MANIFEST.in
README.markdown
setup.py
django_vz_wiki.egg-info/PKG-INFO
django_vz_wiki.egg-info/SOURCES.txt
django_vz_wiki.egg-info/dependency_links.txt
django_vz_wiki.egg-info/top_level.txt
vz_wiki/__init__.py
vz_wiki/admin.py
vz_wiki/exceptions.py
vz_wiki/forms.py
vz_wiki/models.py
vz_wiki/tests.py
vz_wiki/urls.py
vz_wiki/views.py
vz_wiki/templates/404.html
vz_wiki/templates/500.html
vz_wiki/templates/vz_wiki/compare_revisions.html
vz_wiki/templates/vz_wiki/create_page.html
vz_wiki/templates/vz_wiki/edit_page.html
vz_wiki/templates/vz_wiki/page_detail.html
vz_wiki/templates/vz_wiki/page_history.html
vz_wiki/templates/vz_wiki/page_list.html
vz_wiki/templates/vz_wiki/page_tags.html
vz_wiki/templates/vz_wiki/slug.js
vz_wiki/templates/vz_wiki/wiki_menu.html
vz_wiki/templatetags/__init__.py
vz_wiki/templatetags/wiki_tags.py
vz_wiki/utils/__init__.py
vz_wiki/utils/diff_match_patch.py