Metadata-Version: 1.0
Name: django-vz-wiki
Version: 0.1.3
Summary: A Django powered wiki app
Home-page: http://jobscry.net/projects/#vz_wiki
Author: Joe Vasquez
Author-email: joe.vasquez@gmail.com
License: BSD
Download-URL: http://github.com/jobscry/vz-wiki
Platform: UNKNOWN
